open_volara/__init__.py
open_volara/main.py
open_volara/oa_v2.py
open_volara-0.0.4.dist-info/LICENSE
open_volara-0.0.4.dist-info/METADATA
open_volara-0.0.4.dist-info/WHEEL
open_volara-0.0.4.dist-info/RECORD
