Metadata-Version: 2.3
Name: open-volara
Version: 0.0.4
Summary: Volara - Pytorch
License: MIT
Keywords: artificial intelligence,deep learning,optimizers,Prompt Engineering
Author: Kye Gomez
Author-email: kye@apac.ai
Requires-Python: >=3.10,<4.0
Classifier: Development Status :: 4 - Beta
Classifier: Intended Audience :: Developers
Classifier: License :: OSI Approved :: MIT License
Classifier: Programming Language :: Python :: 3
Classifier: Programming Language :: Python :: 3.10
Classifier: Programming Language :: Python :: 3.11
Classifier: Programming Language :: Python :: 3.12
Classifier: Programming Language :: Python :: 3.13
Classifier: Programming Language :: Python :: 3.9
Classifier: Topic :: Scientific/Engineering :: Artificial Intelligence
Requires-Dist: loguru
Requires-Dist: numpy
Requires-Dist: pandas
Requires-Dist: scikit-learn
Requires-Dist: xgboost
Requires-Dist: yfinance
Project-URL: Documentation, https://github.com/The-Swarm-Corporation/Volara
Project-URL: Homepage, https://github.com/The-Swarm-Corporation/Volara
Project-URL: Repository, https://github.com/The-Swarm-Corporation/Volara
